obsutil/__init__.py
obsutil/file.py
obsutil-1.0.4.dist-info/METADATA
obsutil-1.0.4.dist-info/WHEEL
obsutil-1.0.4.dist-info/top_level.txt
obsutil-1.0.4.dist-info/RECORD
